pytest_log/__init__.py
pytest_log-1.0.dist-info/METADATA
pytest_log-1.0.dist-info/WHEEL
pytest_log-1.0.dist-info/entry_points.txt
pytest_log-1.0.dist-info/top_level.txt
pytest_log-1.0.dist-info/RECORD
